pcap2har/__init__.py
pcap2har/main.py
pcap2har-0.1.1.dist-info/METADATA
pcap2har-0.1.1.dist-info/WHEEL
pcap2har-0.1.1.dist-info/entry_points.txt
pcap2har-0.1.1.dist-info/licenses/LICENSE
pcap2har-0.1.1.dist-info/RECORD
