Metadata-Version: 2.4
Name: pcap2har
Version: 0.1.1
Summary: A Python project for converting PCAP files to HAR (HTTP Archive) format
Author-email: Mike Kaplinskiy <mike.kaplinskiy@gmail.com>
License: MIT
License-File: LICENSE
Keywords: analysis,har,http,network,pcap,wireshark
Classifier: Development Status :: 4 - Beta
Classifier: Intended Audience :: Developers
Classifier: License :: OSI Approved :: MIT License
Classifier: Programming Language :: Python :: 3
Classifier: Programming Language :: Python :: 3.10
Classifier: Programming Language :: Python :: 3.11
Classifier: Programming Language :: Python :: 3.12
Classifier: Programming Language :: Python :: 3.13
Classifier: Topic :: Internet :: WWW/HTTP
Classifier: Topic :: Software Development :: Libraries :: Python Modules
Classifier: Topic :: System :: Networking
Requires-Python: >=3.10.0
Requires-Dist: brotli>=1.1.0
Requires-Dist: click>=8.1.0
Requires-Dist: pyshark>=0.6.0
Requires-Dist: tqdm>=4.67.1
